{
  "main": {
    "id": "057cf15846683f24",
    "type": "split",
    "children": [
      {
        "id": "6bcaa125af4ff8c4",
        "type": "tabs",
        "children": [
          {
            "id": "143c3237b25f8bcc",
            "type": "leaf",
            "state": {
              "type": "markdown",
              "state": {
                "file": "review/T.Audio COL4.0-8.md",
                "mode": "source",
                "source": false
              }
            }
          }
        ]
      }
    ],
    "direction": "vertical"
  },
  "left": {
    "id": "afdd7df9bc780315",
    "type": "split",
    "children": [
      {
        "id": "0f6749b3424e279d",
        "type": "tabs",
        "children": [
          {
            "id": "a769cf839cf0865a",
            "type": "leaf",
            "state": {
              "type": "file-explorer",
              "state": {
                "sortOrder": "alphabetical"
              }
            }
          },
          {
            "id": "ad0ff5842c95f68c",
            "type": "leaf",
            "state": {
              "type": "search",
              "state": {
                "query": "",
                "matchingCase": false,
                "explainSearch": false,
                "collapseAll": false,
                "extraContext": false,
                "sortOrder": "alphabetical"
              }
            }
          },
          {
            "id": "8d3775cb711aa86b",
            "type": "leaf",
            "state": {
              "type": "bookmarks",
              "state": {}
            }
          }
        ]
      }
    ],
    "direction": "horizontal",
    "width": 300
  },
  "right": {
    "id": "836ffb3978dc70a7",
    "type": "split",
    "children": [
      {
        "id": "d91fab8a9ebda772",
        "type": "tabs",
        "children": [
          {
            "id": "924b284dfea9bf94",
            "type": "leaf",
            "state": {
              "type": "backlink",
              "state": {
                "file": "review/T.Audio COL4.0-8.md",
                "collapseAll": false,
                "extraContext": false,
                "sortOrder": "alphabetical",
                "showSearch": false,
                "searchQuery": "",
                "backlinkCollapsed": false,
                "unlinkedCollapsed": true
              }
            }
          },
          {
            "id": "664d86e82725b8c0",
            "type": "leaf",
            "state": {
              "type": "outgoing-link",
              "state": {
                "file": "review/T.Audio COL4.0-8.md",
                "linksCollapsed": false,
                "unlinkedCollapsed": true
              }
            }
          },
          {
            "id": "310b02f0ec645efe",
            "type": "leaf",
            "state": {
              "type": "tag",
              "state": {
                "sortOrder": "frequency",
                "useHierarchy": true
              }
            }
          },
          {
            "id": "a63170821b62e29b",
            "type": "leaf",
            "state": {
              "type": "outline",
              "state": {
                "file": "review/T.Audio COL4.0-8.md"
              }
            }
          }
        ]
      }
    ],
    "direction": "horizontal",
    "width": 300,
    "collapsed": true
  },
  "left-ribbon": {
    "hiddenItems": {
      "switcher:Open quick switcher": false,
      "graph:Open graph view": false,
      "canvas:Create new canvas": false,
      "daily-notes:Open today's daily note": false,
      "templates:Insert template": false,
      "command-palette:Open command palette": false
    }
  },
  "active": "143c3237b25f8bcc",
  "lastOpenFiles": [
    "review/Measurement Method.md",
    "review/pic/T.Audio COL4.0/02_03.png",
    "review/pic/T.Audio COL4.0/02_08.png",
    "review/pic/T.Audio COL4.0/VituixCAD Directivity (ver).png",
    "review/pic/T.Audio COL4.0/02_06.png",
    "VOL36_DEC08_Boundaries-1.pdf",
    "review/pic/T.Audio COL4.0/02_04.png",
    "review/pic/T.Audio COL4.0/02_07.png",
    "review/pic/T.Audio COL4.0/02_05.png",
    "review/T.Audio COL4.0-8.md",
    "review/pic/T.Audio COL4.0/02_02.png",
    "review/pic/method/02.png",
    "review/pic/method/03.png",
    "README.md",
    "Standard/TIS1538-2552.pdf",
    "review/pic/method",
    "Sound Engineer/Bass EQ Ep 2.md",
    "Sound Engineer/Bass EQ Ep 1.md",
    "Standard/มอก..md",
    "meterials/Mortar.md",
    "meterials/Plaster of Paris.md",
    "meterials/Rockwool.md",
    "Noise & THD.md",
    "How loud you listen.md",
    "Cables & Connectors.md",
    "AES Anthologies.md",
    "Cable.md",
    "Group Delay - Transients.md",
    "index.md",
    "People.md",
    "Objective Evaluation of Speaker.md",
    "Transient Detection with Absolute Discrete Group Delay.pdf",
    "Standard/ISO_226_2023.pdf",
    "Standard/ISO_226_2003.pdf",
    "Standard/มาตรฐานการวัดลำโพง.md",
    "Dayton/TCP115-4.md",
    "Dayton/Selection.md",
    "Crossover/Inductor.md",
    "Crossover/Type of Crossover.md",
    "Crossover/DIY Inductor results.md",
    "Crossover/Capacitor.md",
    "Spec.mde",
    "Sound Engineer/Sound localization.mde",
    "Sound Engineer/Ear Training 3.mde",
    "Sound Engineer/Ear Training 2.mde"
  ]
}